pgauge/__init__.py
pgauge/__main__.py
pgauge/bench.py
pgauge/parser.py
pgauge-0.7.dist-info/METADATA
pgauge-0.7.dist-info/WHEEL
pgauge-0.7.dist-info/entry_points.txt
pgauge-0.7.dist-info/top_level.txt
pgauge-0.7.dist-info/RECORD
